twenty48tools/Decoder.py
twenty48tools/Encoder.py
twenty48tools/GameReplay.py
twenty48tools/Reporter.py
twenty48tools/Statistics.py
twenty48tools/__init__.py
twenty48tools-0.0.6.dist-info/METADATA
twenty48tools-0.0.6.dist-info/WHEEL
twenty48tools-0.0.6.dist-info/licenses/LICENSE
twenty48tools-0.0.6.dist-info/RECORD
